MANIFEST.in
setup.py
Penguin_static.egg-info/PKG-INFO
Penguin_static.egg-info/SOURCES.txt
Penguin_static.egg-info/dependency_links.txt
Penguin_static.egg-info/entry_points.txt
Penguin_static.egg-info/requires.txt
Penguin_static.egg-info/top_level.txt
penguin/MetadataRenderer.py
penguin/__init__.py
penguin/compiler.py
penguin/main.py
penguin/penguin.py
penguin/post.py
penguin/server.py
penguin/watcher.py
penguin/generator/__init__.py
penguin/generator/about.html
penguin/generator/index.html
penguin/generator/penguin.json
penguin/generator/posts/first.md
penguin/generator/static/main.css
penguin/generator/templates/page.html
penguin/generator/templates/post.html