Metadata-Version: 1.0
Name: Penguin-static
Version: 0.1.2
Summary: Simple static site generator
Home-page: UNKNOWN
Author: Endi Sukaj
Author-email: endisukaj@gmail.com
License: UNKNOWN
Platform: UNKNOWN
